eva/__init__.py
eva/constants.py
eva/eva.yml
eva/eva_cmd_client.py
eva/eva_server.py
eva/binder/__init__.py
eva/binder/binder_utils.py
eva/binder/statement_binder.py
eva/binder/statement_binder_context.py
eva/catalog/__init__.py
eva/catalog/catalog_manager.py
eva/catalog/column_type.py
eva/catalog/df_schema.py
eva/catalog/schema_utils.py
eva/catalog/sql_config.py
eva/catalog/models/__init__.py
eva/catalog/models/base_model.py
eva/catalog/models/df_column.py
eva/catalog/models/df_metadata.py
eva/catalog/models/udf.py
eva/catalog/models/udf_io.py
eva/catalog/services/__init__.py
eva/catalog/services/base_service.py
eva/catalog/services/df_column_service.py
eva/catalog/services/df_service.py
eva/catalog/services/udf_io_service.py
eva/catalog/services/udf_service.py
eva/configuration/__init__.py
eva/configuration/bootstrap_environment.py
eva/configuration/config_utils.py
eva/configuration/configuration_manager.py
eva/configuration/dictionary.py
eva/executor/__init__.py
eva/executor/abstract_executor.py
eva/executor/create_executor.py
eva/executor/create_mat_view_executor.py
eva/executor/create_udf_executor.py
eva/executor/execution_context.py
eva/executor/insert_executor.py
eva/executor/limit_executor.py
eva/executor/load_csv_executor.py
eva/executor/load_executor.py
eva/executor/load_video_executor.py
eva/executor/orderby_executor.py
eva/executor/plan_executor.py
eva/executor/pp_executor.py
eva/executor/sample_executor.py
eva/executor/seq_scan_executor.py
eva/executor/storage_executor.py
eva/executor/union_executor.py
eva/executor/upload_executor.py
eva/expression/__init__.py
eva/expression/abstract_expression.py
eva/expression/aggregation_expression.py
eva/expression/arithmetic_expression.py
eva/expression/comparison_expression.py
eva/expression/constant_value_expression.py
eva/expression/expression_utils.py
eva/expression/function_expression.py
eva/expression/logical_expression.py
eva/expression/tuple_value_expression.py
eva/models/__init__.py
evatestdb-0.0.56.dist-info/LICENSE
evatestdb-0.0.56.dist-info/METADATA
evatestdb-0.0.56.dist-info/WHEEL
evatestdb-0.0.56.dist-info/entry_points.txt
evatestdb-0.0.56.dist-info/top_level.txt
evatestdb-0.0.56.dist-info/RECORD
