Metadata-Version: 2.1
Name: evatestdb
Version: 0.0.56
Summary: EVA is a visual data management system (think MySQL for videos).
Home-page: https://github.com/georgia-tech-db/eva
Author: Georgia Tech Database Group
Author-email: arulraj@gatech.edu
Project-URL: Bug Tracker, https://github.com/georgia-tech-db/eva/issues
Classifier: Programming Language :: Python :: 3
Classifier: License :: OSI Approved :: Apache Software License
Classifier: Operating System :: OS Independent
License-File: LICENSE
Requires-Dist: numpy (==1.20.1)
Requires-Dist: opencv-python (==4.5.1.48)
Requires-Dist: pandas (==1.2.3)
Requires-Dist: torch (==1.7.1)
Requires-Dist: torchvision (==0.8.2)
Requires-Dist: Pillow (==8.1.2)
Requires-Dist: sqlalchemy (==1.3.20)
Requires-Dist: pymysql (==0.10.1)
Requires-Dist: sqlalchemy-utils (==0.36.6)
Requires-Dist: pyspark (==3.0.2)
Requires-Dist: petastorm (==0.9.8)
Requires-Dist: antlr4-python3-runtime (==4.8)
Requires-Dist: pyyaml (==5.1)
